{"$schema":"http://json-schema.org/draft-07/schema#","title":"List loki instances","$id":"http://schema.nethserver.org/cluster/list-loki-instances-output.json","type":"object","required":["instances"],"properties":{"instances":{"type":"array","items":{"type":"object","required":["instance_id","instance_label","node_id","node_label","active","offline"],"properties":{"instance_id":{"type":"string","description":"The Loki instance identifier."},"instance_label":{"type":"string","description":"The Loki instance label, if empty string, there's no label."},"node_id":{"type":"string","description":"The node identifier where the Loki instance is running."},"node_label":{"type":"string","description":"The node label where the Loki instance is running, can be empty."},"active":{"type":"boolean","description":"The Loki instance is the currently active."},"offline":{"type":"boolean","description":"The Loki instance is offline."},"retention_days":{"type":"integer","description":"The retention days for the Loki instance."},"active_from":{"type":"string","format":"date-time","description":"The ISO 8601 date-time when the Loki instance was activated."},"active_to":{"type":"string","format":"date-time","description":"The ISO 8601 date-time when the Loki instance was deactivated."},"cloud_log_manager":{"type":"object","description":"Cloud Log Manager forwarder configuration.","required":["status"],"properties":{"status":{"type":"string","description":"Forwarder state."},"address":{"type":"string","description":"Forwarder address where datas are sent."},"tenant":{"type":"string","description":"Cloud Log Manager internal data."},"last_timestamp":{"type":"string","description":"Timestamp of the last log sent."}}},"syslog":{"type":"object","description":"Syslog forwarder configuration.","required":["status"],"properties":{"status":{"type":"string","description":"Forwarder state."},"address":{"type":"string","description":"Forwarder address where data are sent."},"port":{"type":"string","description":"External server port."},"protocol":{"type":"string","description":"Protocol used to send datas."},"format":{"type":"string","description":"Log format."},"last_timestamp":{"type":"string","description":"Timestamp of the last log sent."}}}}}}}}
